MANIFEST.in
setup.py
docs/HISTORY.txt
src/menhir/__init__.py
src/menhir.contenttype.folder.egg-info/PKG-INFO
src/menhir.contenttype.folder.egg-info/SOURCES.txt
src/menhir.contenttype.folder.egg-info/dependency_links.txt
src/menhir.contenttype.folder.egg-info/namespace_packages.txt
src/menhir.contenttype.folder.egg-info/not-zip-safe
src/menhir.contenttype.folder.egg-info/requires.txt
src/menhir.contenttype.folder.egg-info/top_level.txt
src/menhir/contenttype/__init__.py
src/menhir/contenttype/folder/README.txt
src/menhir/contenttype/folder/__init__.py
src/menhir/contenttype/folder/configure.zcml
src/menhir/contenttype/folder/folder.png
src/menhir/contenttype/folder/folder.py
src/menhir/contenttype/folder/ftesting.zcml
src/menhir/contenttype/folder/tests.py
src/menhir/contenttype/folder/views.py
src/menhir/contenttype/folder/locales/en/LC_MESSAGES/menhir.contenttype.folder.mo
src/menhir/contenttype/folder/locales/en/LC_MESSAGES/menhircontenttypefolder.po
src/menhir/contenttype/folder/locales/fr/LC_MESSAGES/menhir.contenttype.folder.mo
src/menhir/contenttype/folder/locales/fr/LC_MESSAGES/menhir.contenttype.folder.po
src/menhir/contenttype/folder/views_templates/compositeview.pt