Metadata-Version: 1.0
Name: menhir.contenttype.folder
Version: 0.2
Summary: Dolmen contenttype extension : folder
Home-page: http://tracker.trollfot.org/
Author: Souheil Chelfouh
Author-email: souheil@chelfouh.com
License: GPL
Download-URL: http://pypi.python.org/pypi/menhir.contenttype.folder
Keywords: Grok Zope3 CMS Dolmen
Platform: Any
Classifier: Environment :: Web Environment
Classifier: Intended Audience :: Other Audience
Classifier: License :: OSI Approved :: GNU General Public License (GPL)
Classifier: Operating System :: OS Independent
Classifier: Programming Language :: Python
